welqrate/__init__.py
welqrate/dataset.py
welqrate/loader.py
welqrate/rank_prediction.py
welqrate/scheduler.py
welqrate/test.py
welqrate/train.py
welqrate/experiment_utils/__init__.py
welqrate/experiment_utils/gcn_hparams.py
welqrate/experiment_utils/seed_run.py
welqrate/models/__init__.py
welqrate/models/MLP/__init__.py
welqrate/models/MLP/mlp.py
welqrate/models/gnn2d/GAT.py
welqrate/models/gnn2d/GCN.py
welqrate/models/gnn2d/GIN.py
welqrate/models/gnn2d/GNNConv.py
welqrate/models/gnn2d/__init__.py
welqrate/models/gnn3d/DimeNet.py
welqrate/models/gnn3d/SchNet.py
welqrate/models/gnn3d/Spherenet.py
welqrate/models/gnn3d/__init__.py
welqrate/models/smiles/__init__.py
welqrate/models/smiles/smiles2vec.py
welqrate/models/smiles/textcnn.py
welqrate/mol_utils/BCL_dataset.py
welqrate/mol_utils/__init__.py
welqrate/mol_utils/features.py
welqrate/mol_utils/preprocess.py
welqrate/utils/__init__.py
welqrate/utils/evaluation.py
welqrate/utils/plot_loss.py
welqrate-0.1.4.dist-info/METADATA
welqrate-0.1.4.dist-info/WHEEL
welqrate-0.1.4.dist-info/top_level.txt
welqrate-0.1.4.dist-info/RECORD
