Metadata-Version: 2.4
Name: welqrate
Version: 0.1.4
Summary: The official implementation of the WelQrate dataset and benchmark
Home-page: https://github.com/xwang38438/WelQrate.git
Author: Xin Wang, Yunchao Liu
Author-email: xin.wang.1@vanderbilt.edu, lanceknight26@gmail.com
Classifier: Programming Language :: Python :: 3
Classifier: License :: OSI Approved :: MIT License
Classifier: Operating System :: OS Independent
Requires-Python: >=3.9
Requires-Dist: torch==2.1.0
Requires-Dist: torch_geometric==2.3.1
Requires-Dist: matplotlib==3.7.1
Requires-Dist: networkx==2.8.7
Requires-Dist: numpy==1.23
Requires-Dist: pandas==1.4
Requires-Dist: scipy==1.11.0
Requires-Dist: setuptools==68.0.0
Requires-Dist: tqdm==4.65.0
Requires-Dist: rdkit==2023.09.6
Requires-Dist: optuna==4.2.1
Requires-Dist: scikit-learn==1.6.1
Provides-Extra: pyg
Requires-Dist: pyg_lib; extra == "pyg"
Requires-Dist: torch_scatter; extra == "pyg"
Requires-Dist: torch_sparse; extra == "pyg"
Requires-Dist: torch_cluster; extra == "pyg"
Requires-Dist: torch_spline_conv; extra == "pyg"
Dynamic: author
Dynamic: author-email
Dynamic: classifier
Dynamic: description
Dynamic: description-content-type
Dynamic: home-page
Dynamic: provides-extra
Dynamic: requires-dist
Dynamic: requires-python
Dynamic: summary
